Metadata-Version: 2.1
Name: takin
Version: 1.1.2
Summary: A Python Toolkit for File Processing, Text Cleaning and Data Splitting
Home-page: https://github.com/sharejing/Takin
Author: Yimin Jing
Author-email: yymmjing@gmail.com
License: MIT
Keywords: NLP text cleaning file processing data splitting
Platform: UNKNOWN
Classifier: Development Status :: 3 - Alpha
Classifier: Intended Audience :: Developers
Classifier: License :: OSI Approved :: MIT License
Classifier: Topic :: Scientific/Engineering
Classifier: Programming Language :: Python :: 3
Classifier: Programming Language :: Python :: 3.6
Classifier: Programming Language :: Python :: 3.7
Classifier: Programming Language :: Python :: 3.8
Classifier: Programming Language :: Python :: 3.9
Requires-Python: >=3.6.0
License-File: LICENSE
